cemcp/__init__.py
cemcp/server.py
cemcp-0.1.3.dist-info/METADATA
cemcp-0.1.3.dist-info/WHEEL
cemcp-0.1.3.dist-info/entry_points.txt
cemcp-0.1.3.dist-info/RECORD
