Metadata-Version: 2.4
Name: cemcp
Version: 0.1.3
Summary: Add your description here
Author-email: xmq <xmqsvip@qq.com>
Requires-Python: >=3.10
Requires-Dist: bs4>=0.0.2
Requires-Dist: dashscope>=1.23.4
Requires-Dist: dotenv>=0.9.9
Requires-Dist: httpx>=0.28.1
Requires-Dist: mcp[cli]>=1.9.3
